dltkai/__init__.py
dltkai/core.py
dltkai/cv.py
dltkai/nlp.py
dltkai-1.1.2.dist-info/LICENSE
dltkai-1.1.2.dist-info/METADATA
dltkai-1.1.2.dist-info/WHEEL
dltkai-1.1.2.dist-info/top_level.txt
dltkai-1.1.2.dist-info/RECORD
